{
  "sem": {
    "buttons": {
      "label": {
        "typography": {
          "xs": {
            "$type": "typography",
            "$value": "{sys.typography.label.lbl_50}",
            "$description": "label.50"
          },
          "sm": {
            "$type": "typography",
            "$value": "{sys.typography.label.lbl_100}",
            "$description": "label.100"
          },
          "md": {
            "$type": "typography",
            "$value": "{sys.typography.label.lbl_200}",
            "$description": "label.200"
          },
          "lg": {
            "$type": "typography",
            "$value": "{sys.typography.label.lbl_300}",
            "$description": "label.300"
          },
          "xl": {
            "$type": "typography",
            "$value": "{sys.typography.label.lbl_400}",
            "$description": "label.400"
          }
        }
      }
    },
    "forms": {
      "fieldset": {
        "legend": {
          "typography": {
            "sm": {
              "$type": "typography",
              "$value": "{sys.typography.label.lbl_100}",
              "$description": "Apply on forms group-legends eg.: <RadioGroup>"
            },
            "md": {
              "$type": "typography",
              "$value": "{sys.typography.label.lbl_200}",
              "$description": "Apply on forms group-legends eg.: <RadioGroup>"
            },
            "lg": {
              "$type": "typography",
              "$value": "{sys.typography.label.lbl_300}",
              "$description": "Apply on forms group-legends eg.: <RadioGroup>"
            }
          }
        }
      },
      "inputfield": {
        "placeholder": {
          "typography": {
            "sm": {
              "$type": "typography",
              "$value": "{sys.typography.input.inp_100}"
            },
            "md": {
              "$type": "typography",
              "$value": "{sys.typography.input.inp_200}"
            },
            "lg": {
              "$type": "typography",
              "$value": "{sys.typography.input.inp_300}"
            }
          }
        },
        "prefixsuffix": {
          "typography": {
            "sm": {
              "$type": "typography",
              "$value": "{sys.typography.input.inp_100}"
            },
            "md": {
              "$type": "typography",
              "$value": "{sys.typography.input.inp_200}"
            },
            "lg": {
              "$type": "typography",
              "$value": "{sys.typography.input.inp_300}"
            }
          }
        },
        "userinput": {
          "typography": {
            "sm": {
              "$type": "typography",
              "$value": "{sys.typography.input.inp_100}"
            },
            "md": {
              "$type": "typography",
              "$value": "{sys.typography.input.inp_200}"
            },
            "lg": {
              "$type": "typography",
              "$value": "{sys.typography.input.inp_300}"
            }
          }
        }
      }
    }
  }
}